tapioca_nessus/__init__.py
tapioca_nessus/resource_mapping.py
tapioca_nessus/tapioca_nessus.py
tapioca_nessus-0.1.5.dist-info/METADATA
tapioca_nessus-0.1.5.dist-info/RECORD
tapioca_nessus-0.1.5.dist-info/WHEEL
tapioca_nessus-0.1.5.dist-info/top_level.txt
